README.md
setup.py
tempe_car_accident_attorney/__init__.py
tempe_car_accident_attorney.egg-info/PKG-INFO
tempe_car_accident_attorney.egg-info/SOURCES.txt
tempe_car_accident_attorney.egg-info/dependency_links.txt
tempe_car_accident_attorney.egg-info/top_level.txt