Metadata-Version: 2.4
Name: tempe-car-accident-attorney
Version: 1.0.0
Summary: Tempe car accident legal resource reference.
Home-page: https://tempeazcaraccidentattorney.com/
Author: Las Vegas Car Accident Lawyer
Project-URL: Homepage, https://tempeazcaraccidentattorney.com/
Project-URL: Free Case Review, https://tempeazcaraccidentattorney.com/contact/
Project-URL: Legal Blog, https://tempeazcaraccidentattorney.com/blog/
Dynamic: author
Dynamic: description
Dynamic: description-content-type
Dynamic: home-page
Dynamic: project-url
Dynamic: summary
